pyphotobackups/__init__.py
pyphotobackups/helpers.py
pyphotobackups/main.py
pyphotobackups-0.1.14.dist-info/licenses/LICENSE
pyphotobackups-0.1.14.dist-info/METADATA
pyphotobackups-0.1.14.dist-info/WHEEL
pyphotobackups-0.1.14.dist-info/entry_points.txt
pyphotobackups-0.1.14.dist-info/top_level.txt
pyphotobackups-0.1.14.dist-info/RECORD
