Metadata-Version: 2.4
Name: pyphotobackups
Version: 0.1.14
Summary: command line tool to sync photos from your iPhone and organize them into YYYY-MM folders.
Author-email: hengtseChou <hankthedev@gmail.com>
License-Expression: GPL-3.0-or-later
Project-URL: Homepage, https://github.com/hengtseChou/pyphotobackups
Requires-Python: >=3.9
License-File: LICENSE
Requires-Dist: pillow>=11.2.1
Requires-Dist: tqdm>=4.67.1
Dynamic: license-file
